webuntis_cli/__init__.py
webuntis_cli/__main__.py
webuntis_cli/run.py
webuntis_cli-0.6.6.dist-info/METADATA
webuntis_cli-0.6.6.dist-info/WHEEL
webuntis_cli-0.6.6.dist-info/entry_points.txt
webuntis_cli-0.6.6.dist-info/RECORD
