Metadata-Version: 2.1
Name: webuntis-cli
Version: 0.6.6
Summary: WebUntis CLI
Home-page: https://tbs1-bo.github.io/webuntis_cli/
License: MIT
Keywords: cli,untis,stundenplan,timetable
Author: Marco Bakera
Author-email: marco@bakera.de
Requires-Python: >=3.8,<4.0
Classifier: Development Status :: 5 - Production/Stable
Classifier: Environment :: Console
Classifier: Intended Audience :: Developers
Classifier: Intended Audience :: Education
Classifier: License :: OSI Approved :: MIT License
Classifier: Programming Language :: Python :: 3
Classifier: Programming Language :: Python :: 3.8
Classifier: Programming Language :: Python :: 3.9
Classifier: Programming Language :: Python :: 3.10
Classifier: Programming Language :: Python :: 3.11
Classifier: Programming Language :: Python :: 3.12
Classifier: Topic :: Education
Requires-Dist: webuntis (>=0.1.11,<0.2.0)
